Workbook

Sheet Inputs_Assumptions
A4: Initial Pool Balance | B4: 500000000
A5: Original Term (WAM) | B5: 48
A6: Gross WAC | B6: 0.145
A7: Baseline Annual CPR | B7: 0.12
A8: Baseline Annual CDR | B8: 0.08
A9: Loss Severity (SEV) | B9: =Sensitivity_Matrix!$C$5 -> 0.65
A10: Servicing Fee | B10: 0.005
A12: Default Multiplier (M) | B12: =Sensitivity_Matrix!$C$6 -> 1
A13: Stressed Annual CDR | B13: =B8*B12 -> 0.08
A15: Single Monthly Mortality (SMM) | B15: =1-(1-B7)^(1/12) -> 0.010596241
A16: Monthly Default Rate (MDR) | B16: =1-(1-B13)^(1/12) -> 0.0069243826
A19: Class A Tranche Share | B19: 0.75
A20: Class A Coupon | B20: 0.0575
A21: Class B Tranche Share | B21: 0.17
A22: Class B Coupon | B22: 0.0825
A23: Equity Tranche Share | B23: 0.08

Sheet Pool_Amortization
A7: Period | B7: Beginning Balance | C7: Gross Interest | D7: Scheduled Principal | E7: Prepayments | F7: Gross Defaults | G7: Net Losses | H7: Recoveries | I7: Total Principal Cash | J7: Total Available Cash | K7: Ending Balance
A8: 0 | K8: =Inputs_Assumptions!$B$4 -> 500000000
A9: 1 | B9: =K8 -> 500000000 | C9: =B9*(Inputs_Assumptions!$B$6/12) -> 6041666.7 | D9: =IF(B9<=0,0,MIN(B9,PPMT(Inputs_Assumptions!$B$6/12,A9,Inputs_Assumptions!$B$5,-Inputs_Assumptions!$B$4))) -> 7747309.8 | E9: =MAX(0,(B9-D9)*Inputs_Assumptions!$B$15) -> 5216028.2 | F9: =B9*Inputs_Assumptions!$B$16 -> 3462191.3 | G9: =F9*Inputs_Assumptions!$B$9 -> 2250424.4 | H9: =F9*(1-Inputs_Assumptions!$B$9) -> 1211767 | I9: =D9+E9 -> 12963338 | J9: =C9+D9+E9+H9 -> 20216772 | K9: =MAX(0,B9-D9-E9-F9) -> 4.8357447e+08
A10: =A9+1 -> 2 | B10: =K9 -> 4.8357447e+08 | C10: =B10*(Inputs_Assumptions!$B$6/12) -> 5843191.5 | D10: =IF(B10<=0,0,MIN(B10,PPMT(Inputs_Assumptions!$B$6/12,1,Inputs_Assumptions!$B$5-A10+1,-B10))) -> 7702690.7 | E10: =MAX(0,(B10-D10)*Inputs_Assumptions!$B$15) -> 5042452.1 | F10: =B10*Inputs_Assumptions!$B$16 -> 3348454.7 | G10: =F10*Inputs_Assumptions!$B$9 -> 2176495.5 | H10: =F10*(1-Inputs_Assumptions!$B$9) -> 1171959.1 | I10: =D10+E10 -> 12745143 | J10: =C10+D10+E10+H10 -> 19760293 | K10: =MAX(0,B10-D10-E10-F10) -> 4.6748087e+08
A11: =A10+1 -> 3 | B11: =K10 -> 4.6748087e+08 | C11: =B11*(Inputs_Assumptions!$B$6/12) -> 5648727.2 | D11: =IF(B11<=0,0,MIN(B11,PPMT(Inputs_Assumptions!$B$6/12,1,Inputs_Assumptions!$B$5-A11+1,-B11))) -> 7658304.5 | E11: =MAX(0,(B11-D11)*Inputs_Assumptions!$B$15) -> 4872390.8 | F11: =B11*Inputs_Assumptions!$B$16 -> 3237016.4 | G11: =F11*Inputs_Assumptions!$B$9 -> 2104060.7 | H11: =F11*(1-Inputs_Assumptions!$B$9) -> 1132955.8 | I11: =D11+E11 -> 12530695 | J11: =C11+D11+E11+H11 -> 19312378 | K11: =MAX(0,B11-D11-E11-F11) -> 4.5171316e+08
A12: =A11+1 -> 4 | B12: =K11 -> 4.5171316e+08 | C12: =B12*(Inputs_Assumptions!$B$6/12) -> 5458200.7 | D12: =IF(B12<=0,0,MIN(B12,PPMT(Inputs_Assumptions!$B$6/12,1,Inputs_Assumptions!$B$5-A12+1,-B12))) -> 7614148.9 | E12: =MAX(0,(B12-D12)*Inputs_Assumptions!$B$15) -> 4705780.2 | F12: =B12*Inputs_Assumptions!$B$16 -> 3127834.8 | G12: =F12*Inputs_Assumptions!$B$9 -> 2033092.6 | H12: =F12*(1-Inputs_Assumptions!$B$9) -> 1094742.2 | I12: =D12+E12 -> 12319929 | J12: =C12+D12+E12+H12 -> 18872872 | K12: =MAX(0,B12-D12-E12-F12) -> 4.362654e+08
A13: =A12+1 -> 5 | B13: =K12 -> 4.362654e+08 | C13: =B13*(Inputs_Assumptions!$B$6/12) -> 5271540.2 | D13: =IF(B13<=0,0,MIN(B13,PPMT(Inputs_Assumptions!$B$6/12,1,Inputs_Assumptions!$B$5-A13+1,-B13))) -> 7570221.7 | E13: =MAX(0,(B13-D13)*Inputs_Assumptions!$B$15) -> 4542557.4 | F13: =B13*Inputs_Assumptions!$B$16 -> 3020868.5 | G13: =F13*Inputs_Assumptions!$B$9 -> 1963564.6 | H13: =F13*(1-Inputs_Assumptions!$B$9) -> 1057304 | I13: =D13+E13 -> 12112779 | J13: =C13+D13+E13+H13 -> 18441623 | K13: =MAX(0,B13-D13-E13-F13) -> 4.2113175e+08
A14: =A13+1 -> 6 | B14: =K13 -> 4.2113175e+08 | C14: =B14*(Inputs_Assumptions!$B$6/12) -> 5088675.3 | D14: =IF(B14<=0,0,MIN(B14,PPMT(Inputs_Assumptions!$B$6/12,1,Inputs_Assumptions!$B$5-A14+1,-B14))) -> 7526520.7 | E14: =MAX(0,(B14-D14)*Inputs_Assumptions!$B$15) -> 4382660.7 | F14: =B14*Inputs_Assumptions!$B$16 -> 2916077.4 | G14: =F14*Inputs_Assumptions!$B$9 -> 1895450.3 | H14: =F14*(1-Inputs_Assumptions!$B$9) -> 1020627.1 | I14: =D14+E14 -> 11909181 | J14: =C14+D14+E14+H14 -> 18018484 | K14: =MAX(0,B14-D14-E14-F14) -> 4.0630649e+08
A15: =A14+1 -> 7 | B15: =K14 -> 4.0630649e+08 | C15: =B15*(Inputs_Assumptions!$B$6/12) -> 4909536.8 | D15: =IF(B15<=0,0,MIN(B15,PPMT(Inputs_Assumptions!$B$6/12,1,Inputs_Assumptions!$B$5-A15+1,-B15))) -> 7483043.5 | E15: =MAX(0,(B15-D15)*Inputs_Assumptions!$B$15) -> 4226029.4 | F15: =B15*Inputs_Assumptions!$B$16 -> 2813421.6 | G15: =F15*Inputs_Assumptions!$B$9 -> 1828724 | H15: =F15*(1-Inputs_Assumptions!$B$9) -> 984697.56 | I15: =D15+E15 -> 11709073 | J15: =C15+D15+E15+H15 -> 17603307 | K15: =MAX(0,B15-D15-E15-F15) -> 3.91784e+08
A16: =A15+1 -> 8 | B16: =K15 -> 3.91784e+08 | C16: =B16*(Inputs_Assumptions!$B$6/12) -> 4734056.6 | D16: =IF(B16<=0,0,MIN(B16,PPMT(Inputs_Assumptions!$B$6/12,1,Inputs_Assumptions!$B$5-A16+1,-B16))) -> 7439787.9 | E16: =MAX(0,(B16-D16)*Inputs_Assumptions!$B$15) -> 4072603.9 | F16: =B16*Inputs_Assumptions!$B$16 -> 2712862.3 | G16: =F16*Inputs_Assumptions!$B$9 -> 1763360.5 | H16: =F16*(1-Inputs_Assumptions!$B$9) -> 949501.81 | I16: =D16+E16 -> 11512392 | J16: =C16+D16+E16+H16 -> 17195950 | K16: =MAX(0,B16-D16-E16-F16) -> 3.7755874e+08
A17: =A16+1 -> 9 | B17: =K16 -> 3.7755874e+08 | C17: =B17*(Inputs_Assumptions!$B$6/12) -> 4562168.1 | D17: =IF(B17<=0,0,MIN(B17,PPMT(Inputs_Assumptions!$B$6/12,1,Inputs_Assumptions!$B$5-A17+1,-B17))) -> 7396751.3 | E17: =MAX(0,(B17-D17)*Inputs_Assumptions!$B$15) -> 3922325.7 | F17: =B17*Inputs_Assumptions!$B$16 -> 2614361.2 | G17: =F17*Inputs_Assumptions!$B$9 -> 1699334.8 | H17: =F17*(1-Inputs_Assumptions!$B$9) -> 915026.42 | I17: =D17+E17 -> 11319077 | J17: =C17+D17+E17+H17 -> 16796272 | K17: =MAX(0,B17-D17-E17-F17) -> 3.636253e+08
A18: =A17+1 -> 10 | B18: =K17 -> 3.636253e+08 | C18: =B18*(Inputs_Assumptions!$B$6/12) -> 4393805.8 | D18: =IF(B18<=0,0,MIN(B18,PPMT(Inputs_Assumptions!$B$6/12,1,Inputs_Assumptions!$B$5-A18+1,-B18))) -> 7353931.2 | E18: =MAX(0,(B18-D18)*Inputs_Assumptions!$B$15) -> 3775137.3 | F18: =B18*Inputs_Assumptions!$B$16 -> 2517880.7 | G18: =F18*Inputs_Assumptions!$B$9 -> 1636622.5 | H18: =F18*(1-Inputs_Assumptions!$B$9) -> 881258.26 | I18: =D18+E18 -> 11129069 | J18: =C18+D18+E18+H18 -> 16404133 | K18: =MAX(0,B18-D18-E18-F18) -> 3.4997836e+08
A19: =A18+1 -> 11 | B19: =K18 -> 3.4997836e+08 | C19: =B19*(Inputs_Assumptions!$B$6/12) -> 4228905.1 | D19: =IF(B19<=0,0,MIN(B19,PPMT(Inputs_Assumptions!$B$6/12,1,Inputs_Assumptions!$B$5-A19+1,-B19))) -> 7311325.1 | E19: =MAX(0,(B19-D19)*Inputs_Assumptions!$B$15) -> 3630982.4 | F19: =B19*Inputs_Assumptions!$B$16 -> 2423384 | G19: =F19*Inputs_Assumptions!$B$9 -> 1575199.6 | H19: =F19*(1-Inputs_Assumptions!$B$9) -> 848184.42 | I19: =D19+E19 -> 10942308 | J19: =C19+D19+E19+H19 -> 16019397 | K19: =MAX(0,B19-D19-E19-F19) -> 3.3661266e+08
A20: =A19+1 -> 12 | B20: =K19 -> 3.3661266e+08 | C20: =B20*(Inputs_Assumptions!$B$6/12) -> 4067403 | D20: =IF(B20<=0,0,MIN(B20,PPMT(Inputs_Assumptions!$B$6/12,1,Inputs_Assumptions!$B$5-A20+1,-B20))) -> 7268930.2 | E20: =MAX(0,(B20-D20)*Inputs_Assumptions!$B$15) -> 3489805.6 | F20: =B20*Inputs_Assumptions!$B$16 -> 2330834.9 | G20: =F20*Inputs_Assumptions!$B$9 -> 1515042.7 | H20: =F20*(1-Inputs_Assumptions!$B$9) -> 815792.21 | I20: =D20+E20 -> 10758736 | J20: =C20+D20+E20+H20 -> 15641931 | K20: =MAX(0,B20-D20-E20-F20) -> 3.2352309e+08
A21: =A20+1 -> 13 | B21: =K20 -> 3.2352309e+08 | C21: =B21*(Inputs_Assumptions!$B$6/12) -> 3909237.4 | D21: =IF(B21<=0,0,MIN(B21,PPMT(Inputs_Assumptions!$B$6/12,1,Inputs_Assumptions!$B$5-A21+1,-B21))) -> 7226743.7 | E21: =MAX(0,(B21-D21)*Inputs_Assumptions!$B$15) -> 3351552.4 | F21: =B21*Inputs_Assumptions!$B$16 -> 2240197.7 | G21: =F21*Inputs_Assumptions!$B$9 -> 1456128.5 | H21: =F21*(1-Inputs_Assumptions!$B$9) -> 784069.19 | I21: =D21+E21 -> 10578296 | J21: =C21+D21+E21+H21 -> 15271603 | K21: =MAX(0,B21-D21-E21-F21) -> 3.107046e+08
... A56: =A55+1 -> 48 | B56: =K55 -> 5765217.3 | C56: =B56*(Inputs_Assumptions!$B$6/12) -> 69663.042 | D56: =IF(B56<=0,0,MIN(B56,PPMT(Inputs_Assumptions!$B$6/12,1,Inputs_Assumptions!$B$5-A56+1,-B56))) -> 5765217.3 | E56: =MAX(0,(B56-D56)*Inputs_Assumptions!$B$15) -> 0 | F56: =B56*Inputs_Assumptions!$B$16 -> 39920.57 | G56: =F56*Inputs_Assumptions!$B$9 -> 25948.371 | H56: =F56*(1-Inputs_Assumptions!$B$9) -> 13972.2 | I56: =D56+E56 -> 5765217.3 | J56: =C56+D56+E56+H56 -> 5848852.5 | K56: =MAX(0,B56-D56-E56-F56) -> 0

Sheet Waterfall_Cashflows
A7: Period | B7: Class A Balance | C7: Class B Balance | D7: Equity Balance | E7: Senior Servicing Fee | F7: Cash Available After Fees | G7: Class A Interest Due & Paid | H7: Cash After Class A Interest | I7: Class B Interest Due & Paid | J7: Available Principal Collections | K7: Class A Principal Paid | L7: Class B Principal Paid | M7: Equity Loss Absorption | P7: Class A Ending Balance | S7: Residual / Excess Spread Distribution to Equity | V7: Tranche | W7: Original Balance | X7: Principal Repaid | Y7: Principal Written Down | Z7: Interest / Residual Paid | AA7: Impairment %
A8: 0 | B8: =Inputs_Assumptions!$B$4*Inputs_Assumptions!$B$19 -> 375000000 | C8: =Inputs_Assumptions!$B$4*Inputs_Assumptions!$B$21 -> 85000000 | D8: =Inputs_Assumptions!$B$4*Inputs_Assumptions!$B$23 -> 40000000 | V8: Class A | W8: =B8 -> 375000000 | X8: =SUM(K9:K56) -> 375000000 | Y8: =SUM(O9:O56) -> 0 | Z8: =SUM(G9:G56) -> 32304168 | AA8: =Y8/W8 -> 0
A9: =A8+1 -> 1 | B9: =MAX(0,B8-K9-O9) -> 3.6203666e+08 | C9: =MAX(0,C8-L9-N9) -> 85000000 | D9: =MAX(0,D8-M9) -> 37749576 | E9: =Pool_Amortization!B9*(Inputs_Assumptions!$B$10/12) -> 208333.33 | F9: =MAX(0,Pool_Amortization!J9-E9) -> 20008438 | G9: =MIN(F9,B8*(Inputs_Assumptions!$B$20/12)) -> 1796875 | H9: =F9-G9 -> 18211563 | I9: =MIN(H9,C8*(Inputs_Assumptions!$B$22/12)) -> 584375 | J9: =Pool_Amortization!I9 -> 12963338 | K9: =MIN(J9,B8) -> 12963338 | L9: =MIN(MAX(0,J9-K9),C8) -> 0 | M9: =MIN(Pool_Amortization!G9,D8) -> 2250424.4 | N9: =MIN(MAX(0,Pool_Amortization!G9-M9),C8-L9) -> 0 | O9: =MIN(MAX(0,Pool_Amortization!G9-M9-N9),B8-K9) -> 0 | P9: =MAX(0,B8-K9-O9) -> 3.6203666e+08 | Q9: =MAX(0,C8-L9-N9) -> 85000000 | R9: =MAX(0,D8-M9) -> 37749576 | S9: =MAX(0,H9-I9-K9-L9) -> 4663850.3 | V9: Class B | W9: =C8 -> 85000000 | X9: =SUM(L9:L56) -> 54395279 | Y9: =SUM(N9:N56) -> 5919017.2 | Z9: =SUM(I9:I56) -> 26051355 | AA9: =Y9/W9 -> 0.069635496
A10: =A9+1 -> 2 | B10: =MAX(0,B9-K10-O10) -> 3.4929152e+08 | C10: =MAX(0,C9-L10-N10) -> 85000000 | D10: =MAX(0,D9-M10) -> 35573080 | E10: =Pool_Amortization!B10*(Inputs_Assumptions!$B$10/12) -> 201489.36 | F10: =MAX(0,Pool_Amortization!J10-E10) -> 19558804 | G10: =MIN(F10,B9*(Inputs_Assumptions!$B$20/12)) -> 1734759 | H10: =F10-G10 -> 17824045 | I10: =MIN(H10,C9*(Inputs_Assumptions!$B$22/12)) -> 584375 | J10: =Pool_Amortization!I10 -> 12745143 | K10: =MIN(J10,B9) -> 12745143 | L10: =MIN(MAX(0,J10-K10),C9) -> 0 | M10: =MIN(Pool_Amortization!G10,D9) -> 2176495.5 | N10: =MIN(MAX(0,Pool_Amortization!G10-M10),C9-L10) -> 0 | O10: =MIN(MAX(0,Pool_Amortization!G10-M10-N10),B9-K10) -> 0 | P10: =MAX(0,B9-K10-O10) -> 3.4929152e+08 | Q10: =MAX(0,C9-L10-N10) -> 85000000 | R10: =MAX(0,D9-M10) -> 35573080 | S10: =MAX(0,H10-I10-K10-L10) -> 4494527.3 | V10: Equity | W10: =D8 -> 40000000 | X10: =0 -> 0 | Y10: =SUM(M9:M56) -> 40000000 | Z10: =SUM(S9:S56) -> 85650498 | AA10: =Y10/W10 -> 1
A11: =A10+1 -> 3 | B11: =MAX(0,B10-K11-O11) -> 3.3676082e+08 | C11: =MAX(0,C10-L11-N11) -> 85000000 | D11: =MAX(0,D10-M11) -> 33469019 | E11: =Pool_Amortization!B11*(Inputs_Assumptions!$B$10/12) -> 194783.7 | F11: =MAX(0,Pool_Amortization!J11-E11) -> 19117595 | G11: =MIN(F11,B10*(Inputs_Assumptions!$B$20/12)) -> 1673688.5 | H11: =F11-G11 -> 17443906 | I11: =MIN(H11,C10*(Inputs_Assumptions!$B$22/12)) -> 584375 | J11: =Pool_Amortization!I11 -> 12530695 | K11: =MIN(J11,B10) -> 12530695 | L11: =MIN(MAX(0,J11-K11),C10) -> 0 | M11: =MIN(Pool_Amortization!G11,D10) -> 2104060.7 | N11: =MIN(MAX(0,Pool_Amortization!G11-M11),C10-L11) -> 0 | O11: =MIN(MAX(0,Pool_Amortization!G11-M11-N11),B10-K11) -> 0 | P11: =MAX(0,B10-K11-O11) -> 3.3676082e+08 | Q11: =MAX(0,C10-L11-N11) -> 85000000 | R11: =MAX(0,D10-M11) -> 33469019 | S11: =MAX(0,H11-I11-K11-L11) -> 4328835.7
A12: =A11+1 -> 4 | B12: =MAX(0,B11-K12-O12) -> 3.2444089e+08 | C12: =MAX(0,C11-L12-N12) -> 85000000 | D12: =MAX(0,D11-M12) -> 31435927 | E12: =Pool_Amortization!B12*(Inputs_Assumptions!$B$10/12) -> 188213.82 | F12: =MAX(0,Pool_Amortization!J12-E12) -> 18684658 | G12: =MIN(F12,B11*(Inputs_Assumptions!$B$20/12)) -> 1613645.6 | H12: =F12-G12 -> 17071012 | I12: =MIN(H12,C11*(Inputs_Assumptions!$B$22/12)) -> 584375 | J12: =Pool_Amortization!I12 -> 12319929 | K12: =MIN(J12,B11) -> 12319929 | L12: =MIN(MAX(0,J12-K12),C11) -> 0 | M12: =MIN(Pool_Amortization!G12,D11) -> 2033092.6 | N12: =MIN(MAX(0,Pool_Amortization!G12-M12),C11-L12) -> 0 | O12: =MIN(MAX(0,Pool_Amortization!G12-M12-N12),B11-K12) -> 0 | P12: =MAX(0,B11-K12-O12) -> 3.2444089e+08 | Q12: =MAX(0,C11-L12-N12) -> 85000000 | R12: =MAX(0,D11-M12) -> 31435927 | S12: =MAX(0,H12-I12-K12-L12) -> 4166708.4
A13: =A12+1 -> 5 | B13: =MAX(0,B12-K13-O13) -> 3.1232812e+08 | C13: =MAX(0,C12-L13-N13) -> 85000000 | D13: =MAX(0,D12-M13) -> 29472362 | E13: =Pool_Amortization!B13*(Inputs_Assumptions!$B$10/12) -> 181777.25 | F13: =MAX(0,Pool_Amortization!J13-E13) -> 18259846 | G13: =MIN(F13,B12*(Inputs_Assumptions!$B$20/12)) -> 1554612.6 | H13: =F13-G13 -> 16705233 | I13: =MIN(H13,C12*(Inputs_Assumptions!$B$22/12)) -> 584375 | J13: =Pool_Amortization!I13 -> 12112779 | K13: =MIN(J13,B12) -> 12112779 | L13: =MIN(MAX(0,J13-K13),C12) -> 0 | M13: =MIN(Pool_Amortization!G13,D12) -> 1963564.6 | N13: =MIN(MAX(0,Pool_Amortization!G13-M13),C12-L13) -> 0 | O13: =MIN(MAX(0,Pool_Amortization!G13-M13-N13),B12-K13) -> 0 | P13: =MAX(0,B12-K13-O13) -> 3.1232812e+08 | Q13: =MAX(0,C12-L13-N13) -> 85000000 | R13: =MAX(0,D12-M13) -> 29472362 | S13: =MAX(0,H13-I13-K13-L13) -> 4008079.3
A14: =A13+1 -> 6 | B14: =MAX(0,B13-K14-O14) -> 3.0041893e+08 | C14: =MAX(0,C13-L14-N14) -> 85000000 | D14: =MAX(0,D13-M14) -> 27576912 | E14: =Pool_Amortization!B14*(Inputs_Assumptions!$B$10/12) -> 175471.56 | F14: =MAX(0,Pool_Amortization!J14-E14) -> 17843012 | G14: =MIN(F14,B13*(Inputs_Assumptions!$B$20/12)) -> 1496572.2 | H14: =F14-G14 -> 16346440 | I14: =MIN(H14,C13*(Inputs_Assumptions!$B$22/12)) -> 584375 | J14: =Pool_Amortization!I14 -> 11909181 | K14: =MIN(J14,B13) -> 11909181 | L14: =MIN(MAX(0,J14-K14),C13) -> 0 | M14: =MIN(Pool_Amortization!G14,D13) -> 1895450.3 | N14: =MIN(MAX(0,Pool_Amortization!G14-M14),C13-L14) -> 0 | O14: =MIN(MAX(0,Pool_Amortization!G14-M14-N14),B13-K14) -> 0 | P14: =MAX(0,B13-K14-O14) -> 3.0041893e+08 | Q14: =MAX(0,C13-L14-N14) -> 85000000 | R14: =MAX(0,D13-M14) -> 27576912 | S14: =MAX(0,H14-I14-K14-L14) -> 3852883.6
A15: =A14+1 -> 7 | B15: =MAX(0,B14-K15-O15) -> 2.8870986e+08 | C15: =MAX(0,C14-L15-N15) -> 85000000 | D15: =MAX(0,D14-M15) -> 25748188 | E15: =Pool_Amortization!B15*(Inputs_Assumptions!$B$10/12) -> 169294.37 | F15: =MAX(0,Pool_Amortization!J15-E15) -> 17434013 | G15: =MIN(F15,B14*(Inputs_Assumptions!$B$20/12)) -> 1439507.4 | H15: =F15-G15 -> 15994505 | I15: =MIN(H15,C14*(Inputs_Assumptions!$B$22/12)) -> 584375 | J15: =Pool_Amortization!I15 -> 11709073 | K15: =MIN(J15,B14) -> 11709073 | L15: =MIN(MAX(0,J15-K15),C14) -> 0 | M15: =MIN(Pool_Amortization!G15,D14) -> 1828724 | N15: =MIN(MAX(0,Pool_Amortization!G15-M15),C14-L15) -> 0 | O15: =MIN(MAX(0,Pool_Amortization!G15-M15-N15),B14-K15) -> 0 | P15: =MAX(0,B14-K15-O15) -> 2.8870986e+08 | Q15: =MAX(0,C14-L15-N15) -> 85000000 | R15: =MAX(0,D14-M15) -> 25748188 | S15: =MAX(0,H15-I15-K15-L15) -> 3701057.6
A16: =A15+1 -> 8 | B16: =MAX(0,B15-K16-O16) -> 2.7719747e+08 | C16: =MAX(0,C15-L16-N16) -> 85000000 | D16: =MAX(0,D15-M16) -> 23984827 | E16: =Pool_Amortization!B16*(Inputs_Assumptions!$B$10/12) -> 163243.33 | F16: =MAX(0,Pool_Amortization!J16-E16) -> 17032707 | G16: =MIN(F16,B15*(Inputs_Assumptions!$B$20/12)) -> 1383401.4 | H16: =F16-G16 -> 15649305 | I16: =MIN(H16,C15*(Inputs_Assumptions!$B$22/12)) -> 584375 | J16: =Pool_Amortization!I16 -> 11512392 | K16: =MIN(J16,B15) -> 11512392 | L16: =MIN(MAX(0,J16-K16),C15) -> 0 | M16: =MIN(Pool_Amortization!G16,D15) -> 1763360.5 | N16: =MIN(MAX(0,Pool_Amortization!G16-M16),C15-L16) -> 0 | O16: =MIN(MAX(0,Pool_Amortization!G16-M16-N16),B15-K16) -> 0 | P16: =MAX(0,B15-K16-O16) -> 2.7719747e+08 | Q16: =MAX(0,C15-L16-N16) -> 85000000 | R16: =MAX(0,D15-M16) -> 23984827 | S16: =MAX(0,H16-I16-K16-L16) -> 3552538.7
A17: =A16+1 -> 9 | B17: =MAX(0,B16-K17-O17) -> 2.6587839e+08 | C17: =MAX(0,C16-L17-N17) -> 85000000 | D17: =MAX(0,D16-M17) -> 22285493 | E17: =Pool_Amortization!B17*(Inputs_Assumptions!$B$10/12) -> 157316.14 | F17: =MAX(0,Pool_Amortization!J17-E17) -> 16638955 | G17: =MIN(F17,B16*(Inputs_Assumptions!$B$20/12)) -> 1328237.9 | H17: =F17-G17 -> 15310718 | I17: =MIN(H17,C16*(Inputs_Assumptions!$B$22/12)) -> 584375 | J17: =Pool_Amortization!I17 -> 11319077 | K17: =MIN(J17,B16) -> 11319077 | L17: =MIN(MAX(0,J17-K17),C16) -> 0 | M17: =MIN(Pool_Amortization!G17,D16) -> 1699334.8 | N17: =MIN(MAX(0,Pool_Amortization!G17-M17),C16-L17) -> 0 | O17: =MIN(MAX(0,Pool_Amortization!G17-M17-N17),B16-K17) -> 0 | P17: =MAX(0,B16-K17-O17) -> 2.6587839e+08 | Q17: =MAX(0,C16-L17-N17) -> 85000000 | R17: =MAX(0,D16-M17) -> 22285493 | S17: =MAX(0,H17-I17-K17-L17) -> 3407265.5
A18: =A17+1 -> 10 | B18: =MAX(0,B17-K18-O18) -> 2.5474932e+08 | C18: =MAX(0,C17-L18-N18) -> 85000000 | D18: =MAX(0,D17-M18) -> 20648870 | E18: =Pool_Amortization!B18*(Inputs_Assumptions!$B$10/12) -> 151510.54 | F18: =MAX(0,Pool_Amortization!J18-E18) -> 16252622 | G18: =MIN(F18,B17*(Inputs_Assumptions!$B$20/12)) -> 1274000.6 | H18: =F18-G18 -> 14978621 | I18: =MIN(H18,C17*(Inputs_Assumptions!$B$22/12)) -> 584375 | J18: =Pool_Amortization!I18 -> 11129069 | K18: =MIN(J18,B17) -> 11129069 | L18: =MIN(MAX(0,J18-K18),C17) -> 0 | M18: =MIN(Pool_Amortization!G18,D17) -> 1636622.5 | N18: =MIN(MAX(0,Pool_Amortization!G18-M18),C17-L18) -> 0 | O18: =MIN(MAX(0,Pool_Amortization!G18-M18-N18),B17-K18) -> 0 | P18: =MAX(0,B17-K18-O18) -> 2.5474932e+08 | Q18: =MAX(0,C17-L18-N18) -> 85000000 | R18: =MAX(0,D17-M18) -> 20648870 | S18: =MAX(0,H18-I18-K18-L18) -> 3265177.8
A19: =A18+1 -> 11 | B19: =MAX(0,B18-K19-O19) -> 2.4380702e+08 | C19: =MAX(0,C18-L19-N19) -> 85000000 | D19: =MAX(0,D18-M19) -> 19073671 | E19: =Pool_Amortization!B19*(Inputs_Assumptions!$B$10/12) -> 145824.31 | F19: =MAX(0,Pool_Amortization!J19-E19) -> 15873573 | G19: =MIN(F19,B18*(Inputs_Assumptions!$B$20/12)) -> 1220673.8 | H19: =F19-G19 -> 14652899 | I19: =MIN(H19,C18*(Inputs_Assumptions!$B$22/12)) -> 584375 | J19: =Pool_Amortization!I19 -> 10942308 | K19: =MIN(J19,B18) -> 10942308 | L19: =MIN(MAX(0,J19-K19),C18) -> 0 | M19: =MIN(Pool_Amortization!G19,D18) -> 1575199.6 | N19: =MIN(MAX(0,Pool_Amortization!G19-M19),C18-L19) -> 0 | O19: =MIN(MAX(0,Pool_Amortization!G19-M19-N19),B18-K19) -> 0 | P19: =MAX(0,B18-K19-O19) -> 2.4380702e+08 | Q19: =MAX(0,C18-L19-N19) -> 85000000 | R19: =MAX(0,D18-M19) -> 19073671 | S19: =MAX(0,H19-I19-K19-L19) -> 3126216.4
A20: =A19+1 -> 12 | B20: =MAX(0,B19-K20-O20) -> 2.3304828e+08 | C20: =MAX(0,C19-L20-N20) -> 85000000 | D20: =MAX(0,D19-M20) -> 17558628 | E20: =Pool_Amortization!B20*(Inputs_Assumptions!$B$10/12) -> 140255.28 | F20: =MAX(0,Pool_Amortization!J20-E20) -> 15501676 | G20: =MIN(F20,B19*(Inputs_Assumptions!$B$20/12)) -> 1168242 | H20: =F20-G20 -> 14333434 | I20: =MIN(H20,C19*(Inputs_Assumptions!$B$22/12)) -> 584375 | J20: =Pool_Amortization!I20 -> 10758736 | K20: =MIN(J20,B19) -> 10758736 | L20: =MIN(MAX(0,J20-K20),C19) -> 0 | M20: =MIN(Pool_Amortization!G20,D19) -> 1515042.7 | N20: =MIN(MAX(0,Pool_Amortization!G20-M20),C19-L20) -> 0 | O20: =MIN(MAX(0,Pool_Amortization!G20-M20-N20),B19-K20) -> 0 | P20: =MAX(0,B19-K20-O20) -> 2.3304828e+08 | Q20: =MAX(0,C19-L20-N20) -> 85000000 | R20: =MAX(0,D19-M20) -> 17558628 | S20: =MAX(0,H20-I20-K20-L20) -> 2990323
A21: =A20+1 -> 13 | B21: =MAX(0,B20-K21-O21) -> 2.2246998e+08 | C21: =MAX(0,C20-L21-N21) -> 85000000 | D21: =MAX(0,D20-M21) -> 16102499 | E21: =Pool_Amortization!B21*(Inputs_Assumptions!$B$10/12) -> 134801.29 | F21: =MAX(0,Pool_Amortization!J21-E21) -> 15136801 | G21: =MIN(F21,B20*(Inputs_Assumptions!$B$20/12)) -> 1116689.7 | H21: =F21-G21 -> 14020112 | I21: =MIN(H21,C20*(Inputs_Assumptions!$B$22/12)) -> 584375 | J21: =Pool_Amortization!I21 -> 10578296 | K21: =MIN(J21,B20) -> 10578296 | L21: =MIN(MAX(0,J21-K21),C20) -> 0 | M21: =MIN(Pool_Amortization!G21,D20) -> 1456128.5 | N21: =MIN(MAX(0,Pool_Amortization!G21-M21),C20-L21) -> 0 | O21: =MIN(MAX(0,Pool_Amortization!G21-M21-N21),B20-K21) -> 0 | P21: =MAX(0,B20-K21-O21) -> 2.2246998e+08 | Q21: =MAX(0,C20-L21-N21) -> 85000000 | R21: =MAX(0,D20-M21) -> 16102499 | S21: =MAX(0,H21-I21-K21-L21) -> 2857440.6
A22: =A21+1 -> 14 | B22: =MAX(0,B21-K22-O22) -> 2.1206905e+08 | C22: =MAX(0,C21-L22-N22) -> 85000000 | D22: =MAX(0,D21-M22) -> 14704065 | E22: =Pool_Amortization!B22*(Inputs_Assumptions!$B$10/12) -> 129460.25 | F22: =MAX(0,Pool_Amortization!J22-E22) -> 14778822 | G22: =MIN(F22,B21*(Inputs_Assumptions!$B$20/12)) -> 1066002 | H22: =F22-G22 -> 13712820 | I22: =MIN(H22,C21*(Inputs_Assumptions!$B$22/12)) -> 584375 | J22: =Pool_Amortization!I22 -> 10400932 | K22: =MIN(J22,B21) -> 10400932 | L22: =MIN(MAX(0,J22-K22),C21) -> 0 | M22: =MIN(Pool_Amortization!G22,D21) -> 1398434.4 | N22: =MIN(MAX(0,Pool_Amortization!G22-M22),C21-L22) -> 0 | O22: =MIN(MAX(0,Pool_Amortization!G22-M22-N22),B21-K22) -> 0 | P22: =MAX(0,B21-K22-O22) -> 2.1206905e+08 | Q22: =MAX(0,C21-L22-N22) -> 85000000 | R22: =MAX(0,D21-M22) -> 14704065 | S22: =MAX(0,H22-I22-K22-L22) -> 2727513.1
... A56: =A55+1 -> 48 | B56: =MAX(0,B55-K56-O56) -> 0 | C56: =MAX(0,C55-L56-N56) -> 24685704 | D56: =MAX(0,D55-M56) -> 0 | E56: =Pool_Amortization!B56*(Inputs_Assumptions!$B$10/12) -> 2402.1739 | F56: =MAX(0,Pool_Amortization!J56-E56) -> 5846450.3 | G56: =MIN(F56,B55*(Inputs_Assumptions!$B$20/12)) -> 0 | H56: =F56-G56 -> 5846450.3 | I56: =MIN(H56,C55*(Inputs_Assumptions!$B$22/12)) -> 209528.48 | J56: =Pool_Amortization!I56 -> 5765217.3 | K56: =MIN(J56,B55) -> 0 | L56: =MIN(MAX(0,J56-K56),C55) -> 5765217.3 | M56: =MIN(Pool_Amortization!G56,D55) -> 0 | N56: =MIN(MAX(0,Pool_Amortization!G56-M56),C55-L56) -> 25948.371 | O56: =MIN(MAX(0,Pool_Amortization!G56-M56-N56),B55-K56) -> 0 | P56: =MAX(0,B55-K56-O56) -> 0 | Q56: =MAX(0,C55-L56-N56) -> 24685704 | R56: =MAX(0,D55-M56) -> 0 | S56: =MAX(0,H56-I56-K56-L56) -> 0

Sheet Sensitivity_Matrix
B2: Sensitivity Test / What-If Analysis
B4: Active Test Inputs | I4: Current Test Outputs
B5: Loss Severity (SEV) | C5: 0.65 | D5: Base Case Reference | E5: 0.65 | I5: Class B Impairment | J5: =Waterfall_Cashflows!$AA$9 -> 0.069635496
B6: Default Multiplier (M) | C6: 1 | D6: Base Case Reference | E6: 1 | I6: Equity Impairment | J6: =Waterfall_Cashflows!$AA$10 -> 1
I7: Class B Ending Balance | J7: =Waterfall_Cashflows!$Q$56 -> 24685704
B8: Class B Impairment Sensitivity | I8: Pool Ending Balance | J8: =Pool_Amortization!$K$56 -> 0
A9: Default Multiplier / Loss Severity | B9: =Waterfall_Cashflows!$AA$9 -> 0.069635496 | C9: 0.55 | D9: 0.6 | E9: 0.65 | F9: 0.7 | G9: 0.75
B10: 1 | C10: 0 | D10: 0.028079824 | E10: 0.069635496 | F10: 0.11119117 | G10: 0.15274684 | I10: Reset Instructions
B11: 1.2 | C11: 0.070664659 | D11: 0.11986947 | E11: 0.16907428 | F11: 0.21827909 | G11: 0.26748389 | I11: Set C5 = E5 and C6 = E6 to restore base case.
B12: 1.4 | C12: 0.15250161 | D12: 0.20914614 | E12: 0.26579067 | F12: 0.32243521 | G12: 0.37907974
B13: 1.6 | C13: 0.23208694 | D13: 0.2959665 | E13: 0.35984606 | F13: 0.42372562 | G13: 0.48760518
B14: 1.8 | C14: 0.30947201 | D14: 0.38038658 | E14: 0.45130115 | F14: 0.52221571 | G14: 0.59313028
B15: 2 | C15: 0.38470766 | D15: 0.46246183 | E15: 0.54021601 | F15: 0.61797018 | G15: 0.69572435
B16: 2.2 | C16: 0.45784417 | D16: 0.54224711 | E16: 0.62665006 | F16: 0.711053 | G16: 0.79545595
